pycodetimer/__init__.py
pycodetimer/timer.py
pycodetimer-0.0.2.dist-info/LICENSE
pycodetimer-0.0.2.dist-info/METADATA
pycodetimer-0.0.2.dist-info/WHEEL
pycodetimer-0.0.2.dist-info/top_level.txt
pycodetimer-0.0.2.dist-info/RECORD
