Metadata-Version: 2.1
Name: pycodetimer
Version: 0.0.2
Summary: Python Code Timer
Home-page: https://github.com/LucienShui/pycodetimer
Author: Lucien Shui
Author-email: lucien@lucien.ink
License: UNKNOWN
Platform: UNKNOWN
